greetsub/__init__.py
greetsub/greetinner.py
greetyq-0.1.0.dist-info/METADATA
greetyq-0.1.0.dist-info/WHEEL
greetyq-0.1.0.dist-info/top_level.txt
greetyq-0.1.0.dist-info/RECORD
