Metadata-Version: 2.4
Name: greetyq
Version: 0.1.0
Summary: 杨强的第二个测试,yangq's second test package
Requires-Python: >=3.9
Requires-Dist: dotenv>=0.9.9
Requires-Dist: requests>=2.32.4
